dsmr/__init__.py
dsmr/cli.py
dsmr/datalogger.py
dsmr/dsmr/__init__.py
dsmr/plugins/__init__.py
dsmr/plugins/pvoutput.py
dsmr/telegram/__init__.py
pyproject.toml
dsmr_data_logger-0.1.16.dist-info/entry_points.txt
dsmr_data_logger-0.1.16.dist-info/LICENSE.txt
dsmr_data_logger-0.1.16.dist-info/WHEEL
dsmr_data_logger-0.1.16.dist-info/METADATA
dsmr_data_logger-0.1.16.dist-info/RECORD
